LICENSE.txt
NOTICE.txt
open_source_licenses.txt
cluster_scripts/__init__.py
cluster_scripts/v1_x/__init__.py
cluster_scripts/v1_x/control_plane.sh
cluster_scripts/v1_x/node.sh
cluster_scripts/v2_x/__init__.py
cluster_scripts/v2_x/control_plane.sh
cluster_scripts/v2_x/node.sh
cluster_scripts/v2_x_tkgm/__init__.py
cluster_scripts/v2_x_tkgm/cloud_init_control_plane.yaml
cluster_scripts/v2_x_tkgm/cloud_init_node.yaml
cluster_scripts/v2_x_tkgm/control_plane.sh
container_service_extension/__init__.py
container_service_extension/developer_guide.md
container_service_extension/client/__init__.py
container_service_extension/client/cluster.py
container_service_extension/client/cluster_commands.py
container_service_extension/client/command_filter.py
container_service_extension/client/constants.py
container_service_extension/client/cse.py
container_service_extension/client/de_cluster.py
container_service_extension/client/de_cluster_native.py
container_service_extension/client/de_cluster_tkg_s.py
container_service_extension/client/legacy_cluster_native.py
container_service_extension/client/metadata_based_ovdc.py
container_service_extension/client/node_commands.py
container_service_extension/client/ovdc.py
container_service_extension/client/ovdc_commands.py
container_service_extension/client/pks.py
container_service_extension/client/pks_cluster.py
container_service_extension/client/pks_ovdc.py
container_service_extension/client/policy_based_ovdc.py
container_service_extension/client/sample_generator.py
container_service_extension/client/system.py
container_service_extension/client/system_commands.py
container_service_extension/client/template.py
container_service_extension/client/template_commands.py
container_service_extension/client/utils.py
container_service_extension/client/cse_client/__init__.py
container_service_extension/client/cse_client/cse_client.py
container_service_extension/client/cse_client/pks_cluster_api.py
container_service_extension-3.1.4.dist-info/AUTHORS
container_service_extension-3.1.4.dist-info/LICENSE.txt
container_service_extension-3.1.4.dist-info/METADATA
container_service_extension-3.1.4.dist-info/NOTICE.txt
container_service_extension-3.1.4.dist-info/WHEEL
container_service_extension-3.1.4.dist-info/entry_points.txt
container_service_extension-3.1.4.dist-info/pbr.json
container_service_extension-3.1.4.dist-info/top_level.txt
container_service_extension-3.1.4.dist-info/RECORD
