Metadata-Version: 2.1
Name: container-service-extension
Version: 3.1.4
Summary: Container Service Extension for vCloud Director
Home-page: https://github.com/vmware/container-service-extension
Author: Paco Gomez
Author-email: pgomez@vmware.com
License: BSD-2
Classifier: Environment :: Console
Classifier: Intended Audience :: System Administrators
Classifier: Intended Audience :: Developers
Classifier: Operating System :: POSIX :: Linux
Classifier: Operating System :: MacOS :: MacOS X
Classifier: Operating System :: Microsoft :: Windows
Classifier: Programming Language :: Python
Classifier: Programming Language :: Python :: 3
Requires-Python: >= 3.7
License-File: LICENSE.txt
License-File: NOTICE.txt
License-File: AUTHORS
Requires-Dist: cachetools (<4.0.0,>=3.1.1)
Requires-Dist: certifi (<2021.0.0,>=2020.12.5)
Requires-Dist: click (<8.0.0,>=7.1.2)
Requires-Dist: cryptography (<4.0,>=3.4.8)
Requires-Dist: dataclasses-json (<1.0.0,>=0.5.6)
Requires-Dist: humanfriendly (<5.0,>=4.8)
Requires-Dist: lru-dict (<2.0.0,>=1.1.7)
Requires-Dist: lxml (<5.0.0,>=4.6.3)
Requires-Dist: paho-mqtt (<1.6.0,>=1.5.1)
Requires-Dist: pika (<2.0.0,>=1.2.0)
Requires-Dist: pyvcloud (<23.1.0,>=23.0.4)
Requires-Dist: pyvmomi (<7.0.0,>=6.7.3)
Requires-Dist: PyYaml (<=6.0.0,>=5.4.1)
Requires-Dist: requests (<3.0.0,>=2.26.0)
Requires-Dist: semantic-version (<3.0.0,>=2.8.5)
Requires-Dist: six (<2.0.0,>=1.16.0)
Requires-Dist: urllib3 (<2.0.0,>=1.26.6)
Requires-Dist: validators (~=0.18.2)
Requires-Dist: vcd-cli (<25.0.0,>=24.1.0)
Requires-Dist: vsphere-guest-run (<1.0.0,>=0.0.7)
